mcp_stock_analysis/__init__.py
mcp_stock_analysis/server.py
mcp_stock_analysis-0.1.1.dist-info/METADATA
mcp_stock_analysis-0.1.1.dist-info/WHEEL
mcp_stock_analysis-0.1.1.dist-info/entry_points.txt
mcp_stock_analysis-0.1.1.dist-info/RECORD
