Metadata-Version: 2.4
Name: mcp-stock-analysis
Version: 0.1.1
Summary: MCP server for stock portfolio analysis and reporting
Requires-Python: >=3.11
Requires-Dist: beautifulsoup4>=4.12.3
Requires-Dist: fastmcp>=2.10.6
Requires-Dist: mcp[cli]>=1.12.2
Requires-Dist: numpy>=2.3.2
Requires-Dist: pandas>=2.3.1
Requires-Dist: requests>=2.31.0
Requires-Dist: yfinance>=0.2.65
